Examples/mini_regions.sv
// Sample 1 — mini_regions.sv
// From: "SystemVerilog Scheduling Semantics" paper in Docs
// Demonstrates visibility across scheduler regions (ACTIVE, INACTIVE, POSTPONED)
// This example appears in Section III: Illustrative Example

`timescale 1 ns/1 ns
module mini_regions();

bit clk=0, a=0;
initial forever #5 clk = ~clk;

always_ff @(posedge clk) a <= ~a;

always @(posedge clk) begin
  $display("%0t ACTIVE a=%0b", $time, a);
  #0 $display("%0t INACTIVE a=%0b", $time, a);
end

always @(posedge clk) $strobe("%0t POSTPONED a=%0b", $time, a);

initial #100 $finish;

endmodule : mini_regions

waves/waves.vcd
$date
	Thu Oct 16 15:43:26 2025
$end
$version
	QuestaSim Version 2021.1
$end
$timescale
	1ns
$end

$scope module mini_regions $end
$var reg 1 ! clk $end
$var reg 1 " a $end
$upscope $end
$enddefinitions $end
#0
$dumpvars
0!
0"
$end
#5
1!
1"
#10
0!
#15
1!
0"
#20
0!
#25
1!
1"
#30
0!
#35
1!
0"
#40
0!
#45
1!
1"
#50
0!
#55
1!
0"
#60
0!
#65
1!
1"
#70
0!
#75
1!
0"
#80
0!
#85
1!
1"
#90
0!
#95
1!
0"
